pyicat_plus/__init__.py
pyicat_plus/concurrency.py
pyicat_plus/apps/__init__.py
pyicat_plus/apps/icat_as_nexus.py
pyicat_plus/apps/store_from_file.py
pyicat_plus/apps/store_processed.py
pyicat_plus/apps/store_raw.py
pyicat_plus/apps/sync_raw.py
pyicat_plus/client/__init__.py
pyicat_plus/client/add_files.py
pyicat_plus/client/archive.py
pyicat_plus/client/bliss.py
pyicat_plus/client/defaults.py
pyicat_plus/client/deprecation_utils.py
pyicat_plus/client/elogbook.py
pyicat_plus/client/icatplus_restricted.py
pyicat_plus/client/interface.py
pyicat_plus/client/investigation.py
pyicat_plus/client/main.py
pyicat_plus/client/messaging.py
pyicat_plus/client/metadata.py
pyicat_plus/client/null.py
pyicat_plus/client/serialize.py
pyicat_plus/client/types.py
pyicat_plus/client/update_metadata.py
pyicat_plus/client/xmlns.py
pyicat_plus/client/models/__init__.py
pyicat_plus/client/models/session.py
pyicat_plus/metadata/__init__.py
pyicat_plus/metadata/definitions.py
pyicat_plus/metadata/hdf5_cfg.xml
pyicat_plus/metadata/namespace_wrapper.py
pyicat_plus/metadata/nexus.py
pyicat_plus/tests/__init__.py
pyicat_plus/tests/conftest.py
pyicat_plus/tests/test_cli.py
pyicat_plus/tests/test_elogbook.py
pyicat_plus/tests/test_icat_add_files.py
pyicat_plus/tests/test_icat_archive.py
pyicat_plus/tests/test_icat_datasets.py
pyicat_plus/tests/test_icat_definitions.py
pyicat_plus/tests/test_icat_investigations.py
pyicat_plus/tests/test_icat_mockup.py
pyicat_plus/tests/test_icat_nexus.py
pyicat_plus/tests/test_icat_restricted.py
pyicat_plus/tests/test_icat_serialize.py
pyicat_plus/tests/test_icat_sync.py
pyicat_plus/tests/test_icat_update_metadata.py
pyicat_plus/tests/test_maxsizedict.py
pyicat_plus/tests/test_namespace.py
pyicat_plus/tests/test_raw_data.py
pyicat_plus/tests/test_url_utils.py
pyicat_plus/tests/fixtures/__init__.py
pyicat_plus/tests/fixtures/icat.py
pyicat_plus/tests/fixtures/misc.py
pyicat_plus/tests/fixtures/proc.py
pyicat_plus/tests/fixtures/tcp.py
pyicat_plus-1.0.1.dist-info/licenses/LICENSE.md
pyicat_plus-1.0.1.dist-info/METADATA
pyicat_plus-1.0.1.dist-info/WHEEL
pyicat_plus-1.0.1.dist-info/entry_points.txt
pyicat_plus-1.0.1.dist-info/top_level.txt
pyicat_plus-1.0.1.dist-info/RECORD
