Metadata-Version: 2.4
Name: pyicat-plus
Version: 1.0.1
Summary: Python client to ICAT+
Author-email: ESRF <dau-pydev@esrf.fr>
License: GNU Lesser General Public License
Project-URL: Homepage, https://gitlab.esrf.fr/icat/pyicat-plus/
Project-URL: Documentation, https://pyicat-plus.readthedocs.io/
Project-URL: Repository, https://gitlab.esrf.fr/icat/pyicat-plus/
Project-URL: Issues, https://gitlab.esrf.fr/icat/pyicat-plus/issues
Project-URL: Changelog, https://gitlab.esrf.fr/icat/pyicat-plus/-/blob/main/CHANGELOG.md
Classifier: Intended Audience :: Science/Research
Classifier: License :: OSI Approved :: GNU Lesser General Public License v3 (LGPLv3)
Classifier: Programming Language :: Python :: 3
Requires-Python: >=3.8
License-File: LICENSE.md
Requires-Dist: esrf-ontologies
Requires-Dist: esrf-pathlib
Requires-Dist: h5py
Requires-Dist: icat-esrf-definitions
Requires-Dist: numpy
Requires-Dist: querypool
Requires-Dist: requests
Requires-Dist: stompest
Requires-Dist: tqdm
Provides-Extra: bliss
Requires-Dist: blissdata[beacon]; extra == "bliss"
Provides-Extra: test
Requires-Dist: pyicat-plus[bliss]; extra == "test"
Requires-Dist: pytest>=7; extra == "test"
Requires-Dist: pytest-timeout>=2.1; extra == "test"
Requires-Dist: numpy>=1.15; extra == "test"
Requires-Dist: psutil; extra == "test"
Requires-Dist: coilmq; extra == "test"
Requires-Dist: stomp.py>=7; extra == "test"
Requires-Dist: xmltodict; extra == "test"
Requires-Dist: h5py>=3.5; extra == "test"
Provides-Extra: dev
Requires-Dist: pyicat-plus[test]; extra == "dev"
Requires-Dist: black>=25; extra == "dev"
Requires-Dist: flake8>=4; extra == "dev"
Requires-Dist: pep8-naming; extra == "dev"
Requires-Dist: isort; extra == "dev"
Provides-Extra: doc
Requires-Dist: pyicat-plus[test]; extra == "doc"
Requires-Dist: sphinx>=4.5; extra == "doc"
Requires-Dist: sphinx-autodoc-typehints>=1.16; extra == "doc"
Requires-Dist: pydata-sphinx-theme; extra == "doc"
Requires-Dist: sphinx-copybutton; extra == "doc"
Dynamic: license-file
